examples/__init__.py
examples/buy_and_hold_backtest.py
examples/monthly_liquidate_rebalance_backtest.py
examples/moving_average_cross_backtest.py
examples/test_examples.py
qstrader/__init__.py
qstrader/compat.py
qstrader/event.py
qstrader/exception.py
qstrader/portfolio.py
qstrader/portfolio_handler.py
qstrader/position.py
qstrader/price_parser.py
qstrader/profiling.py
qstrader/settings.py
qstrader/trading_session.py
qstrader/version.py
qstrader/compliance/__init__.py
qstrader/compliance/base.py
qstrader/compliance/example.py
qstrader/execution_handler/__init__.py
qstrader/execution_handler/base.py
qstrader/execution_handler/ib_simulated.py
qstrader/order/__init__.py
qstrader/order/suggested.py
qstrader/position_sizer/__init__.py
qstrader/position_sizer/base.py
qstrader/position_sizer/fixed.py
qstrader/position_sizer/naive.py
qstrader/position_sizer/rebalance.py
qstrader/price_handler/__init__.py
qstrader/price_handler/base.py
qstrader/price_handler/generic.py
qstrader/price_handler/historic_csv_tick.py
qstrader/price_handler/ig.py
qstrader/price_handler/iq_feed_intraday_csv_bar.py
qstrader/price_handler/yahoo_daily_csv_bar.py
qstrader/price_handler/iterator/__init__.py
qstrader/price_handler/iterator/base.py
qstrader/price_handler/iterator/pandas/__init__.py
qstrader/price_handler/iterator/pandas/bar.py
qstrader/price_handler/iterator/pandas/tick.py
qstrader/risk_manager/__init__.py
qstrader/risk_manager/base.py
qstrader/risk_manager/example.py
qstrader/scripts/__init__.py
qstrader/scripts/generate_simulated_prices.py
qstrader/scripts/test_scripts.py
qstrader/sentiment_handler/__init__.py
qstrader/sentiment_handler/base.py
qstrader/sentiment_handler/sentdex_sentiment_handler.py
qstrader/statistics/__init__.py
qstrader/statistics/base.py
qstrader/statistics/performance.py
qstrader/statistics/simple.py
qstrader/statistics/tearsheet.py
qstrader/strategy/__init__.py
qstrader/strategy/base.py
qstrader_pro-1.1.5.dist-info/LICENSE
qstrader_pro-1.1.5.dist-info/METADATA
qstrader_pro-1.1.5.dist-info/WHEEL
qstrader_pro-1.1.5.dist-info/top_level.txt
qstrader_pro-1.1.5.dist-info/RECORD
